{
  "id": 4844,
  "title": "EIP-4844: Shard Blob Transactions",
  "status": "Final",
  "description": "Shard Blob Transactions scale data-availability of Ethereum in a simple, forwards-compatible manner.",
  "author": "Vitalik Buterin (@vbuterin), Dankrad Feist (@dankrad), Diederik Loerakker (@protolambda), George Kadianakis (@asn-d6), Matt Garnett (@lightclient), Mofi Taiwo (@Inphi), Ansgar Dietrichs (@adietrichs)",
  "type": "Standards Track",
  "category": "Core",
  "createdDate": "2022-02-25",
  "discussionLink": "https://ethereum-magicians.org/t/eip-4844-shard-blob-transactions/",
  "reviewer": "bot",
  "forkRelationships": [
    {
      "forkName": "Dencun",
      "statusHistory": [
        {
          "status": "Included",
          "call": null,
          "date": null
        }
      ]
    }
  ]
}
